{"16_22_12_2017":{"min":12,"max":35,"avg":18,"median":15,"mode":0},"14_2_1_2018":{"min":10,"max":60,"avg":22,"median":20,"mode":0},"15_2_1_2018":{"min":10,"max":60,"avg":22,"median":20,"mode":0},"16_2_1_2018":{"min":10,"max":60,"avg":22,"median":20,"mode":0},"10_3_1_2018":{"min":10,"max":60,"avg":17,"median":15,"mode":0},"11_3_1_2018":{"min":10,"max":60,"avg":17,"median":15,"mode":0},"14_19_1_2018":{"min":10,"max":75,"avg":31,"median":30,"mode":0},"15_23_1_2018":{"min":10,"max":75,"avg":27,"median":20,"mode":0},"14_26_1_2018":{"min":10,"max":60,"avg":25,"median":20,"mode":0}}