{"16_22_12_2017":{"min":33,"max":125,"avg":102,"median":125,"mode":0},"14_2_1_2018":{"min":15,"max":430,"avg":208,"median":180,"mode":0},"15_2_1_2018":{"min":15,"max":430,"avg":208,"median":180,"mode":0},"16_2_1_2018":{"min":15,"max":430,"avg":208,"median":180,"mode":0},"10_3_1_2018":{"min":10,"max":430,"avg":158,"median":97,"mode":0},"11_3_1_2018":{"min":10,"max":430,"avg":158,"median":97,"mode":0},"14_19_1_2018":{"min":15,"max":230,"avg":155,"median":230,"mode":0},"15_23_1_2018":{"min":73,"max":230,"avg":183,"median":215,"mode":0},"14_26_1_2018":{"min":200,"max":200,"avg":200,"median":200,"mode":0}}