{"17_18_12_2017":{"min":7,"max":7,"avg":7,"median":7,"mode":7},"16_22_12_2017":{"min":5,"max":5,"avg":5,"median":5,"mode":5},"14_2_1_2018":{"min":7,"max":7,"avg":7,"median":7,"mode":7},"15_2_1_2018":{"min":5,"max":7,"avg":6,"median":6,"mode":7},"16_2_1_2018":{"min":5,"max":7,"avg":6,"median":6,"mode":7},"10_3_1_2018":{"min":5,"max":10,"avg":7,"median":7,"mode":10},"11_3_1_2018":{"min":5,"max":10,"avg":7,"median":7,"mode":10},"13_12_1_2018":{"min":5,"max":5,"avg":5,"median":5,"mode":5},"14_19_1_2018":{"min":5,"max":5,"avg":5,"median":5,"mode":5},"15_26_1_2018":{"min":5,"max":5,"avg":5,"median":5,"mode":5}}