{"16_22_12_2017":{"min":200,"max":850,"avg":628,"median":650,"mode":0},"14_2_1_2018":{"min":200,"max":1000,"avg":645,"median":700,"mode":0},"15_2_1_2018":{"min":200,"max":800,"avg":609,"median":650,"mode":0},"16_2_1_2018":{"min":200,"max":800,"avg":609,"median":650,"mode":0},"10_3_1_2018":{"min":200,"max":850,"avg":596,"median":620,"mode":0},"11_3_1_2018":{"min":200,"max":850,"avg":596,"median":620,"mode":0},"14_19_1_2018":{"min":350,"max":1000,"avg":591,"median":600,"mode":0},"15_23_1_2018":{"min":100,"max":987,"avg":555,"median":600,"mode":0},"14_26_1_2018":{"min":100,"max":700,"avg":478,"median":500,"mode":0}}