{"16_22_12_2017":{"min":100,"max":350,"avg":157,"median":150,"mode":0},"14_2_1_2018":{"min":20,"max":800,"avg":193,"median":150,"mode":0},"15_2_1_2018":{"min":20,"max":800,"avg":193,"median":150,"mode":0},"16_2_1_2018":{"min":20,"max":800,"avg":193,"median":150,"mode":0},"10_3_1_2018":{"min":20,"max":800,"avg":187,"median":150,"mode":0},"11_3_1_2018":{"min":20,"max":800,"avg":187,"median":150,"mode":0},"14_19_1_2018":{"min":100,"max":200,"avg":151,"median":150,"mode":0},"15_23_1_2018":{"min":14,"max":180,"avg":132,"median":150,"mode":0},"14_26_1_2018":{"min":14,"max":1800,"avg":249,"median":150,"mode":0}}